subs_data_scripts/__init__.py
subs_data_scripts-0.0.1.dist-info/METADATA
subs_data_scripts-0.0.1.dist-info/WHEEL
subs_data_scripts-0.0.1.dist-info/top_level.txt
subs_data_scripts-0.0.1.dist-info/RECORD
