Metadata-Version: 2.4
Name: subs-data-scripts
Version: 0.0.1
Summary: Dummy security package to prevent dependency confusion.
Author-email: media-appsec <media-appsec@schibsted.com>
License: MIT
Keywords: security,dependency confusion,placeholder
Classifier: Development Status :: 7 - Inactive
Classifier: Intended Audience :: Developers
Classifier: License :: OSI Approved :: MIT License
Classifier: Topic :: Security
Classifier: Programming Language :: Python :: 3
